<?xml version="1.0" encoding="utf-8" standalone="yes"?>
<gumps>
	<anchored_group_gump matrix_w="1" matrix_h="2">
		<gump type="7" x="914" y="964" serial="1027" name="TargetNearest" graphicId="11546" hideLabel="False" scale="1.4" matrix_x="0" matrix_y="0" />
		<gump type="7" x="914" y="994" serial="1032" name="TargetNearest1" graphicId="11546" hideLabel="False" scale="1.4" matrix_x="0" matrix_y="1" />
	</anchored_group_gump>
	<anchored_group_gump matrix_w="3" matrix_h="3">
		<gump type="7" x="734" y="1032" serial="1017" name="Target Self" graphicId="11546" hideLabel="False" scale="1.4" matrix_x="0" matrix_y="1" />
		<gump type="7" x="823" y="1032" serial="1016" name="Last Target" graphicId="11546" hideLabel="False" scale="1.4" matrix_x="1" matrix_y="1" />
		<gump type="7" x="912" y="1032" serial="1019" name="LastObject" graphicId="11546" hideLabel="False" scale="1.4" matrix_x="2" matrix_y="1" />
	</anchored_group_gump>
	<anchored_group_gump matrix_w="1" matrix_h="2">
		<gump type="7" x="33" y="372" serial="1022" name="InfoItem" graphicId="11546" hideLabel="False" scale="1.2" matrix_x="0" matrix_y="0" />
		<gump type="7" x="33" y="398" serial="1044" name="DroopLoot" graphicId="11546" hideLabel="False" scale="1.2" matrix_x="0" matrix_y="1" />
	</anchored_group_gump>
	<anchored_group_gump matrix_w="2" matrix_h="2">
		<gump type="7" x="24" y="258" serial="1051" name="Fundir" graphicId="725" hideLabel="True" scale="1.6" matrix_x="0" matrix_y="0" />
		<gump type="7" x="24" y="293" serial="1049" name="Minar" graphicId="706" hideLabel="True" scale="1.6" matrix_x="0" matrix_y="1" />
		<gump type="7" x="59" y="293" serial="1050" name="Stop" graphicId="714" hideLabel="True" scale="1.6" matrix_x="1" matrix_y="1" />
	</anchored_group_gump>
	<gump type="9" x="676" y="8" serial="3262917" isminimized="False" />
	<gump type="2" x="693" y="629" serial="1458969872" graphic="61" isminimized="False" />
	<gump type="16" x="595" y="326" serial="0" id="3" />
	<gump type="2" x="413" y="597" serial="1182295987" graphic="75" isminimized="False" />
	<gump type="2" x="685" y="453" serial="1121942032" graphic="60" isminimized="False" />
	<gump type="2" x="660" y="331" serial="1371318332" graphic="60" isminimized="False" />
	<gump type="5" x="28" y="328" serial="1" />
	<gump type="5" x="201" y="13" serial="0" />
	<gump type="24" x="932" y="28" serial="0" />
	<gump type="25" x="774" y="28" serial="0" entryname="skill" />
	<gump type="27" x="860" y="478" serial="0" />
	<gump type="8" x="330" y="0" serial="0" isminimized="False" />
	<gump type="3" x="1879" y="0" serial="0" rows="27" columns="1" rectsize="40">
		<controls>
			<control graphic="3617" hue="0" key="113" mousebutton="0" alt="True" ctrl="False" shift="False" />
			<control graphic="5370" hue="2799" key="119" mousebutton="0" alt="True" ctrl="False" shift="False" />
			<control graphic="3847" hue="0" key="101" mousebutton="0" alt="True" ctrl="False" shift="False" />
			<control graphic="3847" hue="0" key="114" mousebutton="0" alt="True" ctrl="False" shift="False" />
			<control graphic="0" hue="0" key="103" mousebutton="0" alt="False" ctrl="False" shift="False" />
			<control graphic="0" hue="0" />
			<control graphic="0" hue="0" />
			<control graphic="0" hue="0" />
			<control graphic="6585" hue="2419" />
			<control graphic="6585" hue="0" />
			<control graphic="7154" hue="0" />
			<control graphic="5091" hue="0" />
			<control graphic="0" hue="0" />
			<control graphic="0" hue="0" />
			<control graphic="0" hue="0" />
			<control graphic="0" hue="0" />
			<control graphic="0" hue="0" />
			<control graphic="0" hue="0" />
			<control graphic="3973" hue="0" />
			<control graphic="3739" hue="0" />
			<control graphic="11888" hue="0" />
			<control graphic="11884" hue="0" />
			<control graphic="8786" hue="0" />
			<control graphic="24436" hue="0" />
			<control graphic="0" hue="0" />
			<control graphic="0" hue="0" />
			<control graphic="3821" hue="0" />
		</controls>
	</gump>
	<gump type="16" x="1435" y="937" serial="0" id="38" />
	<gump type="1" x="466" y="76" serial="0" graphic="30079" direction="0" />
	<gump type="7" x="224" y="347" serial="1052" name="ItemID&amp;Sort" graphicId="0" hideLabel="False" scale="1" />
	<gump type="12" x="200" y="18" serial="0" />
	<gump type="10" x="-8" y="428" serial="0" isminimized="False" height="315" />
	<gump type="21" x="512" y="872" serial="0" />
	<gump type="18" x="5" y="0" serial="0" />
	<gump type="6" x="-3" y="795" serial="0" />
</gumps>